django_projects/__init__.py
django_projects/djangos/db.sqlite3
django_projects/djangos/manage.py
django_projects/djangos/djangos/__init__.py
django_projects/djangos/djangos/asgi.py
django_projects/djangos/djangos/settings.py
django_projects/djangos/djangos/urls.py
django_projects/djangos/djangos/wsgi.py
djangoprojectstest-0.1.0.dist-info/METADATA
djangoprojectstest-0.1.0.dist-info/WHEEL
djangoprojectstest-0.1.0.dist-info/RECORD
